{
  "USD": "1.1919",
  "JPY": "183.59",
  "CZK": "24.325",
  "DKK": "7.4674",
  "GBP": "0.86620",
  "HUF": "380.70",
  "PLN": "4.2073",
  "RON": "5.0964",
  "SEK": "10.5205",
  "CHF": "0.9157",
  "ISK": "145.20",
  "NOK": "11.3885",
  "TRY": "51.8324",
  "AUD": "1.7001",
  "BRL": "6.2233",
  "CAD": "1.6120",
  "CNY": "8.2834",
  "HKD": "9.3067",
  "IDR": "20010.00",
  "ILS": "3.6799",
  "INR": "109.5825",
  "KRW": "1719.47",
  "MXN": "20.5979",
  "MYR": "4.7044",
  "NZD": "1.9660",
  "PHP": "70.211",
  "SGD": "1.5111",
  "THB": "37.455",
  "ZAR": "18.9906",
  "EUR": "1.0"
}